{
  "type": "pfm:furniture",
  "group": "bedroom",
  "ingredients": [
    {
      "item": "unusualprehistory:ginkgo_planks"
    },
    {
      "item": "unusualprehistory:ginkgo_planks"
    },
    {
      "item": "unusualprehistory:ginkgo_planks"
    },
    {
      "item": "unusualprehistory:ginkgo_planks"
    },
    {
      "item": "unusualprehistory:ginkgo_planks"
    },
    {
      "item": "minecraft:pink_bed"
    }
  ],
  "result": {
    "item": "pfm:ginkgo_unusualprehistory_pink_simple_bed"
  }
}